live/__init__.py
live/clip.py
live/constants.py
live/device.py
live/exceptions.py
live/group.py
live/object.py
live/parameter.py
live/query.py
live/scene.py
live/set.py
live/track.py
pylive-0.2.0.dist-info/METADATA
pylive-0.2.0.dist-info/WHEEL
pylive-0.2.0.dist-info/top_level.txt
pylive-0.2.0.dist-info/RECORD
