Metadata-Version: 2.1
Name: pylive
Version: 0.2.0
Summary: Python remote control of Ableton Live
Home-page: https://github.com/ideoforms/pylive
Author: Daniel Jones
Author-email: dan-pylive@erase.net
License: UNKNOWN
Keywords: sound,music,ableton,osc
Platform: UNKNOWN
Classifier: Topic :: Multimedia :: Sound/Audio
Classifier: Topic :: Artistic Software
Classifier: Topic :: Communications
Classifier: Development Status :: 4 - Beta
Classifier: Intended Audience :: Developers
Requires-Dist: pyliblo (>=0.9.1)
